celitech/__init__.py
celitech/sdk.py
celitech/hooks/__init__.py
celitech/hooks/hook.py
celitech/models/__init__.py
celitech/models/base.py
celitech/models/create_purchase_ok_response.py
celitech/models/create_purchase_request.py
celitech/models/edit_purchase_ok_response.py
celitech/models/edit_purchase_request.py
celitech/models/get_esim_device_ok_response.py
celitech/models/get_esim_history_ok_response.py
celitech/models/get_esim_mac_ok_response.py
celitech/models/get_esim_ok_response.py
celitech/models/get_purchase_consumption_ok_response.py
celitech/models/list_destinations_ok_response.py
celitech/models/list_packages_ok_response.py
celitech/models/list_purchases_ok_response.py
celitech/models/top_up_esim_ok_response.py
celitech/models/top_up_esim_request.py
celitech/models/utils/cast_models.py
celitech/models/utils/json_map.py
celitech/net/__init__.py
celitech/net/environment/__init__.py
celitech/net/environment/environment.py
celitech/net/headers/__init__.py
celitech/net/headers/base_header.py
celitech/net/request_chain/__init__.py
celitech/net/request_chain/request_chain.py
celitech/net/request_chain/handlers/__init__.py
celitech/net/request_chain/handlers/base_handler.py
celitech/net/request_chain/handlers/hook_handler.py
celitech/net/request_chain/handlers/http_handler.py
celitech/net/request_chain/handlers/retry_handler.py
celitech/net/transport/__init__.py
celitech/net/transport/request.py
celitech/net/transport/request_error.py
celitech/net/transport/response.py
celitech/net/transport/serializer.py
celitech/net/transport/utils.py
celitech/services/__init__.py
celitech/services/destinations.py
celitech/services/e_sim.py
celitech/services/packages.py
celitech/services/purchases.py
celitech/services/utils/base_service.py
celitech/services/utils/default_headers.py
celitech/services/utils/validator.py
celitech-1.0.0.dist-info/LICENSE
celitech-1.0.0.dist-info/METADATA
celitech-1.0.0.dist-info/WHEEL
celitech-1.0.0.dist-info/top_level.txt
celitech-1.0.0.dist-info/RECORD
